bazingo/__init__.py
bazingo/bazingo.py
bazingo-0.0.2.dist-info/METADATA
bazingo-0.0.2.dist-info/WHEEL
bazingo-0.0.2.dist-info/top_level.txt
bazingo-0.0.2.dist-info/RECORD
