Metadata-Version: 2.1
Name: bazingo
Version: 0.0.2
Summary: A `Notebook` replacement for tkinter
Home-page: https://github.com/Moosems/bazingo
Author: Moosems
Author-email: moosems.j@gmail.com
